flask_pikarmq/__init__.py
Flask_PikaRMQ-1.0.2.dist-info/LICENSE
Flask_PikaRMQ-1.0.2.dist-info/METADATA
Flask_PikaRMQ-1.0.2.dist-info/WHEEL
Flask_PikaRMQ-1.0.2.dist-info/top_level.txt
Flask_PikaRMQ-1.0.2.dist-info/RECORD
